style_image/__init__.py
style_image/core/__init__.py
style_image/core/style_image.py
style_image/main.py
style_image/util/__init__.py
style_image/util/image_utils.py
style_image-0.1.0.dist-info/entry_points.txt
style_image-0.1.0.dist-info/WHEEL
style_image-0.1.0.dist-info/METADATA
style_image-0.1.0.dist-info/RECORD
