Metadata-Version: 2.1
Name: style-image
Version: 0.1.0
Summary: 
Author: Henry Ruiz 
Author-email: henryruiz22@gmail.com
Requires-Python: >=3.10,<3.11
Classifier: Programming Language :: Python :: 3
Classifier: Programming Language :: Python :: 3.10
Requires-Dist: Pillow (>=9.2.0,<10.0.0)
Requires-Dist: numpy (>=1.23.1,<2.0.0)
Requires-Dist: tensorflow (>=2.9.1,<3.0.0)
Requires-Dist: tensorflow-hub (>=0.12.0,<0.13.0)
Requires-Dist: typer[all] (>=0.6.1,<0.7.0)
Requires-Dist: validators (>=0.20.0,<0.21.0)
